oop_bus/__init__.py
oop_bus/__main__.py
oop_bus/event.py
oop_bus/event_bus.py
oop_bus/event_listener.py
oop_bus/multi_event_listener.py
oop_bus/typed_event_listener.py
oop_event_bus-0.1.0.dist-info/licenses/LICENSE
oop_event_bus-0.1.0.dist-info/METADATA
oop_event_bus-0.1.0.dist-info/WHEEL
oop_event_bus-0.1.0.dist-info/top_level.txt
oop_event_bus-0.1.0.dist-info/RECORD
