Metadata-Version: 2.4
Name: oop-event-bus
Version: 0.1.0
Summary: A simple OOP event bus
Author-email: Volodymyr Chub <v@chub.com.ua>
License: MIT
Project-URL: Homepage, https://github.com/ChubV/oop-event-bus/
Project-URL: Repository, https://github.com/ChubV/oop-event-bus/
Keywords: utils
Requires-Python: >=3.9
License-File: LICENSE
Provides-Extra: dev
Requires-Dist: pytest; extra == "dev"
Requires-Dist: pytest-asyncio; extra == "dev"
Requires-Dist: ruff; extra == "dev"
Dynamic: license-file
